investimentos/__init__.py
investimentos/investimentos.py
investimentos-0.1.dist-info/METADATA
investimentos-0.1.dist-info/WHEEL
investimentos-0.1.dist-info/top_level.txt
investimentos-0.1.dist-info/RECORD
